{
    "leefo1": {
        "title": "LFG202 Duct Carbon Dioxide Transmitter",
        "imgURL": "https://www.lefoo.com/thumb/300/300/produtos/01-6628c9ce47759.jpg"
    },
    "leefo2": {
        "title": "LFG60 All-in-One Air Quality Transmitter",
        "imgURL": "https://www.lefoo.com/thumb/300/300/produtos/1-2-662e031aab0fd.jpg"
    },
    "leefo3": {
        "title": "LFH20 Indoor Temperature and Humidity Transmitter",
        "imgURL": "https://www.lefoo.com/thumb/300/300/produtos/03-662dfd7098bd5.jpg"
    },
    "leefo4": {
        "title": "LFM73 Multi-Function Differential Pressure Transmitter",
        "imgURL": "https://www.lefoo.com/thumb/300/300/produtos/lfm73-2-663ded2485663.jpg"
    },
    "leefo5": {
        "title": "LFW21 Temperature Transmitter",
        "imgURL": "https://www.lefoo.com/thumb/300/300/produtos/-65e9139be337c.jpg"
    },
    "leefo6": {
        "title": "LFZ Standard Rotary Actuator",
        "imgURL": "https://www.lefoo.com/thumb/300/300/produtos/lfz-03.jpg"
    },
    "leefo7": {
        "title": "Temperature and Humidity Sensor LFH10A",
        "imgURL": "https://www.lefoo.com/thumb/300/300/produtos/1-7-63eef3b9c7a1c.jpg"
    },
    "leefo8": {
        "title": "Temperature and Humidity Sensor Probe LFH51",
        "imgURL": "https://www.lefoo.com/thumb/300/300/produtos/02-63f03ecc19fa0.jpg"
    },
    "leefo9": {
        "title": "LF08 Small Multi-Purpose Pressure Switch, 0.2~45bar",
        "imgURL": "https://www.lefoo.com/thumb/300/300/produtos/1-625d062e833fa.png"
    },
    "leefo10": {
        "title": "LFZ-Q Fast Running Rotary Actuator",
        "imgURL": "https://www.lefoo.com/thumb/300/300/produtos/lfz-q-01-649ba6cae524f.jpg"
    },
    "leefo11": {
        "title": "LF20 Extended Duty Pressure Switch, 0.5~150Psi",
        "imgURL": "https://www.lefoo.com/thumb/300/300/produtos/58.jpg"
    },
    "leefo12": {
        "title": "LFZ-DQ Electrical Regulating Ball Valve",
        "imgURL": "https://www.lefoo.com/thumb/300/300/produtos/lfz-dq-649bd0720f2f9.jpg"
    }
}